django_bestzhlocale/__init__.py
django_bestzhlocale/admin.py
django_bestzhlocale/apps.py
django_bestzhlocale/models.py
django_bestzhlocale/urls.py
django_bestzhlocale/views.py
django_bestzhlocale/locale/zh_Hans/LC_MESSAGES/django.mo
django_bestzhlocale/locale/zh_Hans/LC_MESSAGES/django.po
django_bestzhlocale/static/css/django_bestzhlocale.css
django_bestzhlocale/static/js/django_bestzhlocale.js
django_bestzhlocale/templates/django_bestzhlocale/base.html
django_bestzhlocale/test_utils/__init__.py
django_bestzhlocale/test_utils/test_app/__init__.py
django_bestzhlocale/test_utils/test_app/admin.py
django_bestzhlocale/test_utils/test_app/apps.py
django_bestzhlocale/test_utils/test_app/models.py
django_bestzhlocale/test_utils/test_app/migrations/__init__.py
django_bestzhlocale-0.1.1.dist-info/AUTHORS.rst
django_bestzhlocale-0.1.1.dist-info/LICENSE
django_bestzhlocale-0.1.1.dist-info/METADATA
django_bestzhlocale-0.1.1.dist-info/WHEEL
django_bestzhlocale-0.1.1.dist-info/top_level.txt
django_bestzhlocale-0.1.1.dist-info/RECORD
